{
    "id": "redis",
    "name": "Redis 7",
    "description": "高性能内存键值数据库，支持持久化、集群和 Lua 脚本",
    "icon": "fas fa-bolt",
    "image": "images:ubuntu/22.04",
    "min_cpu": 1,
    "min_memory": "1024MiB",
    "min_disk": "10GiB",
    "cloud_init": "apt-get install -y lsb-release gpg\ncurl -fsSL https://packages.redis.io/gpg | gpg --dearmor -o /usr/share/keyrings/redis-archive-keyring.gpg\necho \"deb [signed-by=/usr/share/keyrings/redis-archive-keyring.gpg] https://packages.redis.io/deb $(lsb_release -cs) main\" > /etc/apt/sources.list.d/redis.list\napt-get update\napt-get install -y redis-server\nsed -i 's/^bind .*/bind 0.0.0.0/' /etc/redis/redis.conf\nsed -i 's/^# requirepass .*/requirepass '\"$(openssl rand -base64 24)\"'/' /etc/redis/redis.conf\nsystemctl enable redis-server\nsystemctl restart redis-server",
    "ports": [6379]
}
